pyxcelframe/__init__.py
pyxcelframe/pyxcelframe.py
pyxcelframe-1.6.dist-info/LICENSE
pyxcelframe-1.6.dist-info/METADATA
pyxcelframe-1.6.dist-info/WHEEL
pyxcelframe-1.6.dist-info/top_level.txt
pyxcelframe-1.6.dist-info/RECORD
