Metadata-Version: 2.1
Name: pyxcelframe
Version: 1.6
Summary: Useful tool for more specialized interactions between the Pandas DataFrames and the Excel worksheets
Home-page: https://github.com/lukasanukvari/pyxcelframe
Author: Luka Sosiashvili
Author-email: luksosiashvili@gmail.com
License: MIT License
Platform: UNKNOWN
Classifier: Programming Language :: Python :: 3
Classifier: License :: OSI Approved :: MIT License
Classifier: Operating System :: OS Independent
Requires-Python: >=3.8
License-File: LICENSE
Requires-Dist: pandas
Requires-Dist: openpyxl
